Workbook

Sheet KNVV--BSEG
A1: Company Code | B1: Customer | C1: Customer Name | D1: Current Terms of Payment1 | E1: Current Terms of Payment2 | H1: Quantity 26.01-26.05 | I1: Sales Value | J1: Sales Check and reply Description | K1: Matched or Not | L1: Need correct Part in SAP | M1: SAP term description
A2: 0439 | B2: 1012688 | C2: MARUTI SUZUKI INDIA LIMITED - (GUJ) | D2: 0460 | E2: within 30 days Due net | F2: =VLOOKUP(B2,[1]KNVV!$A:$L,12,0) -> 0460 | G2: =D2=F2 -> TRUE | H2: 221565 | I2: 32629779 | J2: 1 week after delivery | K2: Not Matched | L2: X004 | M2: within 8 days Due net
A3: 0439 | B3: 1012693 | C3: SHREE DHANLAXMI INDUSTRIES | D3: 0460 | E3: within 30 days Due net | F3: =VLOOKUP(B3,[1]KNVV!$A:$L,12,0) -> 0460 | G3: =D3=F3 -> TRUE | H3: 2300 | I3: 285022 | J3: NA | K3: OK
A4: 0439 | B4: 1012598 | C4: Hyundai Motor India Limited | D4: 7604 | E4: within 64 days Due net | F4: =VLOOKUP(B4,[1]KNVV!$A:$L,12,0) -> 7604 | G4: =D4=F4 -> TRUE | H4: 301258 | I4: 49698476 | J4: within 30 days Due net | K4: Not Matched | L4: 0460 | M4: within 30 days Due net
A5: 0439 | B5: 93762 | C5: Schaeffler India Limited(Hosur) | D5: 0460 | E5: within 30 days Due net | F5: =VLOOKUP(B5,[1]KNVV!$A:$L,12,0) -> 0460 | G5: =D5=F5 -> TRUE | H5: 118990 | I5: 13902983 | J5: within 30 days Due net | K5: OK
A6: 0439 | B6: 69886 | C6: Hyundai Motors India Limited | D6: 0460 | E6: within 30 days Due net | F6: =VLOOKUP(B6,[1]KNVV!$A:$L,12,0) -> 0460 | G6: =D6=F6 -> TRUE | H6: 1232754 | I6: 2.8337007e+08 | J6: within 30 days Due net | K6: OK
A7: 0439 | B7: 103309 | C7: CATENSYS India Pvt. Ltd.(Gurugram) | D7: 0201 | E7: Payable immediately Due net | F7: =VLOOKUP(B7,[1]KNVV!$A:$L,12,0) -> 0201 | G7: =D7=F7 -> TRUE | J7: Stock transfer | K7: OK
A8: 0439 | B8: 103310 | C8: CATENSYS India Pvt. Ltd.(Chennai) | D8: 0201 | E8: Payable immediately Due net | F8: =VLOOKUP(B8,[1]KNVV!$A:$L,12,0) -> 0201 | G8: =D8=F8 -> TRUE | J8: Stock transfer | K8: OK
A9: 0439 | B9: 1012588 | C9: Maruti Suzuki India Limited | D9: Z170 | E9: 90 d end of month,payment on 2. of following month | F9: =VLOOKUP(B9,[1]KNVV!$A:$L,12,0) -> Z170 | G9: =D9=F9 -> TRUE | H9: 233896 | I9: 35621248 | J9: 1 week after delivery | K9: Not Matched | L9: X004 | M9: within 8 days Due net
A10: 0439 | B10: 1012483 | C10: CATENSYS India Pvt. Ltd.(Gujrat) | D10: ZI02 | E10: Before 15 in 3 months Due net | F10: =VLOOKUP(B10,[1]KNVV!$A:$L,12,0) -> ZI02 | G10: =D10=F10 -> TRUE | J10: Stock transfer | K10: OK
A11: 0439 | B11: 1012603 | C11: Maruti Suzuki India Limited(G) | D11: Z170 | E11: 90 d end of month,payment on 2. of following month | F11: =VLOOKUP(B11,[1]KNVV!$A:$L,12,0) -> Z170 | G11: =D11=F11 -> TRUE | H11: 288023 | I11: 31727215 | J11: 1 week after delivery | K11: Not Matched | L11: X004 | M11: within 8 days Due net
A12: 0439 | B12: 97570 | C12: Kia India Private Limited | D12: 0460 | E12: within 30 days Due net | F12: =VLOOKUP(B12,[1]KNVV!$A:$L,12,0) -> 0460 | G12: =D12=F12 -> TRUE | H12: 217246 | I12: 40370680 | J12: within 30 days Due net | K12: OK
A13: 0439 | B13: 77944 | C13: Renault Nissan Automotive India Pvt | D13: 0540 | E13: within 60 days Due net | F13: =VLOOKUP(B13,[1]KNVV!$A:$L,12,0) -> 0540 | G13: =D13=F13 -> TRUE | H13: 96457 | I13: 29265548 | J13: within 60 days Due net | K13: OK
A14: 0439 | B14: 76085 | C14: Honda Cars India Limited | D14: 0535 | E14: within 55 days Due net | F14: =VLOOKUP(B14,[1]KNVV!$A:$L,12,0) -> 0535 | G14: =D14=F14 -> TRUE | H14: 16800 | I14: 909384 | J14: within 55 days Due net | K14: OK
A15: 0439 | B15: 102378 | C15: Mahindra & Mahindra Ltd.(Pune) | D15: 7604 | E15: within 64 days Due net | F15: =VLOOKUP(B15,[1]KNVV!$A:$L,12,0) -> 7604 | G15: =D15=F15 -> TRUE | H15: 48635 | I15: 11079506 | J15: within 64 days Due net | K15: OK
A16: 0439 | B16: 1012484 | C16: KSPG Automotive India Pvt Limited | D16: 7604 | E16: within 64 days Due net | F16: =VLOOKUP(B16,[1]KNVV!$A:$L,12,0) -> 7604 | G16: =D16=F16 -> TRUE | H16: 21839 | I16: 4652199.4 | J16: within 45 days Due net | K16: Not Matched | L16: 0520 | M16: within 45 days Due net
A17: 0439 | B17: 76066 | C17: Maruti Suzuki India Limited -(M) | D17: Z170 | E17: 90 d end of month,payment on 2. of following month | F17: =VLOOKUP(B17,[1]KNVV!$A:$L,12,0) -> Z170 | G17: =D17=F17 -> TRUE | H17: 17540 | I17: 2105894.6 | J17: 1 week after delivery | K17: Not Matched | L17: X004 | M17: within 8 days Due net
A18: 0439 | B18: 56890 | C18: Schaeffler Bearings Indonesia, PT | D18: 0008 | E18: For Invoicing up to 15 of Month, within 14 days 2 % cash discount, within 30 days 1.5 % cash discount, within 45 days Due net, Baseline date on 30 of the month, For Invoicing up to End of Month, within 14 days 2 % cash discount, within 30 days 1.5 % cash discount, within 45 days Due net, Baseline date on 15 of next month | F18: =VLOOKUP(B18,[1]KNVV!$A:$L,12,0) | G18: =D18=F18 -> FALSE | H18: 2880 | I18: 224549.59 | J18: Before 15 in 2 months Due net | K18: Not Matched | L18: Z401 | M18: Before 15 in 2 months Due net
A19: 0439 | B19: 1012568 | C19: ASAHI SANGYO KAISHA LTD | D19: Z910 | E19: Before 15 in 2 months Due net, For Invoicing up to End of Month, Before 15 in 2 months Due net | F19: =VLOOKUP(B19,[1]KNVV!$A:$L,12,0) -> Z910 | G19: =D19=F19 -> TRUE | H19: 78742 | I19: 16081651 | J19: T/T UPON RECEIVED OF GOODS | K19: Not Matched | L19: Z001 | M19: Payable immediately Due net
A20: 0439 | B20: 103052 | C20: CATENSYS Chain Drive (Nanjing) | D20: ZI03 | E20: Before 15 in 2 months Due net | F20: =VLOOKUP(B20,[1]KNVV!$A:$L,12,0) -> ZI03 | G20: =D20=F20 -> TRUE | H20: 33024 | I20: 21905211 | J20: As per IC rules | K20: OK
A21: 0439 | B21: 89654 | C21: Nissan Motor India Private Limited | D21: 0540 | E21: within 60 days Due net | F21: =VLOOKUP(B21,[1]KNVV!$A:$L,12,0) -> 0540 | G21: =D21=F21 -> TRUE | H21: 1530 | I21: 224185.72 | J21: within 60 days Due net | K21: OK
A22: 0439 | B22: 1012433 | C22: KG MOBILITY CORPORATION LTD | D22: 6100 | E22: Payable immediately Due net | F22: =VLOOKUP(B22,[1]KNVV!$A:$L,12,0) -> 6100 | G22: =D22=F22 -> TRUE | H22: 11088 | I22: 9397342.5 | J22: Advance | K22: OK
A23: 0439 | B23: 90577 | C23: Mahindra & Mahindra Limited (JAI) | D23: 7604 | E23: within 64 days Due net | F23: =VLOOKUP(B23,[1]KNVV!$A:$L,12,0) -> 7604 | G23: =D23=F23 -> TRUE | H23: 7685 | I23: 1833588.1 | J23: within 64 days Due net | K23: OK
A24: 0439 | B24: 69472 | C24: Mahindra & Mahindra Limited (Kanhe) | D24: 7604 | E24: within 64 days Due net | F24: =VLOOKUP(B24,[1]KNVV!$A:$L,12,0) -> 7604 | G24: =D24=F24 -> TRUE | H24: 13265 | I24: 3394529.7 | J24: within 64 days Due net | K24: OK
A25: 0439 | B25: 102716 | C25: Mahindra & Mahindra Ltd. (BAN) | D25: 7604 | E25: within 64 days Due net | F25: =VLOOKUP(B25,[1]KNVV!$A:$L,12,0) -> 7604 | G25: =D25=F25 -> TRUE | H25: 3050 | I25: 616320 | J25: within 64 days Due net | K25: OK
A26: 0439 | B26: 69670 | C26: Mahindra & Mahindra Limited (HYD) | D26: 7604 | E26: within 64 days Due net | F26: =VLOOKUP(B26,[1]KNVV!$A:$L,12,0) -> 7604 | G26: =D26=F26 -> TRUE | H26: 1255 | I26: 274605.55 | J26: within 64 days Due net | K26: OK
A27: 0439 | B27: 103056 | C27: CATENSYS India Pvt. Ltd. | D27: 0201 | E27: Payable immediately Due net | F27: =VLOOKUP(B27,[1]KNVV!$A:$L,12,0) -> 0201 | G27: =D27=F27 -> TRUE | J27: NA | K27: OK
A28: 0439 | B28: 100167 | C28: Suzuki Motor Gujarat Pvt. Ltd. | D28: 0460 | E28: within 30 days Due net | F28: =VLOOKUP(B28,[1]KNVV!$A:$L,12,0) -> 0460 | G28: =D28=F28 -> TRUE | H28: -2055 | I28: -197093.59 | J28: 1 week after delivery | K28: Not Matched | L28: X004 | M28: within 8 days Due net
A29: 0439 | B29: 103053 | C29: CATENSYS Korea LLC | D29: ZI03 | E29: Before 15 in 2 months Due net | F29: =VLOOKUP(B29,[1]KNVV!$A:$L,12,0) -> ZI03 | G29: =D29=F29 -> TRUE | H29: 53860 | I29: 9772521 | J29: As per IC rules | K29: OK
A30: 0439 | B30: 69896 | C30: Mobis India Limited | D30: 0460 | E30: within 30 days Due net | F30: =VLOOKUP(B30,[1]KNVV!$A:$L,12,0) -> 0460 | G30: =D30=F30 -> TRUE | H30: 41745 | I30: 9608956.7 | J30: within 30 days Due net | K30: OK
A31: 0439 | B31: 103054 | C31: CATENSYS FRANCE S.A.S. | D31: ZI02 | E31: Before 15 in 3 months Due net | F31: =VLOOKUP(B31,[1]KNVV!$A:$L,12,0) -> ZI02 | G31: =D31=F31 -> TRUE | H31: 39076 | I31: 6069049.4 | J31: As per IC rules | K31: OK
A32: 0439 | B32: 90152 | C32: TVS Motor Company Limited | D32: 0520 | E32: within 45 days Due net | F32: =VLOOKUP(B32,[1]KNVV!$A:$L,12,0) -> 0520 | G32: =D32=F32 -> TRUE | H32: 4632 | I32: 2002077.1 | J32: within 45 days Due net | K32: OK
A33: 0439 | B33: 90767 | C33: Honda Motor India | D33: 0535 | E33: within 55 days Due net | F33: =VLOOKUP(B33,[1]KNVV!$A:$L,12,0) -> 0535 | G33: =D33=F33 -> TRUE | H33: 6072 | I33: 1082141 | J33: within 55 days Due net | K33: OK
A34: 0439 | B34: 1012689 | C34: Mahindra Research Valley(AD) | D34: 0460 | E34: within 30 days Due net | F34: =VLOOKUP(B34,[1]KNVV!$A:$L,12,0) -> 0460 | G34: =D34=F34 -> TRUE | H34: 49 | I34: 586466.45 | J34: within 64 days Due net | K34: Not Matched | L34: 7604 | M34: within 64 days Due net
A35: 0439 | B35: 1012393 | C35: PUNE TRADERS | D35: Z005 | E35: Payable immediately Due net, Baseline date on 10 of next month | F35: =VLOOKUP(B35,[1]KNVV!$A:$L,12,0) -> Z005 | G35: =D35=F35 -> TRUE | H35: 6490 | I35: 145880 | J35: NA | K35: OK
A36: 0439 | B36: 77865 | C36: Maruti Suzuki India Limited(G) | D36: Z170 | E36: 90 d end of month,payment on 2. of following month | F36: =VLOOKUP(B36,[1]KNVV!$A:$L,12,0) -> Z170 | G36: =D36=F36 -> TRUE | J36: 1 week after delivery | K36: Not Matched | L36: X004 | M36: within 8 days Due net

Sheet PaymentTerms in SAP
A1: PayT | B1: Own explanation
A2: 0001 | B2: Payable immediately Due net | C2: =VLOOKUP(A2,'KNVV--BSEG'!D:D,1,0) -> #N/A | D2: =B2 -> Payable immediately Due net
A3: 0002 | B3: within 14 days 2 % cash discount | C3: =VLOOKUP(A3,'KNVV--BSEG'!D:D,1,0) -> #N/A
B4: within 30 days Due net | C4: =VLOOKUP(A4,'KNVV--BSEG'!D:D,1,0) -> #N/A
A5: 0003 | B5: within 14 days 3 % cash discount | C5: =VLOOKUP(A5,'KNVV--BSEG'!D:D,1,0) -> #N/A
B6: within 20 days 2 % cash discount | C6: =VLOOKUP(A6,'KNVV--BSEG'!D:D,1,0) -> #N/A
B7: within 30 days Due net | C7: =VLOOKUP(A7,'KNVV--BSEG'!D:D,1,0) -> #N/A
A8: 0004 | B8: Payable immediately Due net | C8: =VLOOKUP(A8,'KNVV--BSEG'!D:D,1,0) -> #N/A
B9: Baseline date on End of the month | C9: =VLOOKUP(A9,'KNVV--BSEG'!D:D,1,0) -> #N/A
A10: 0005 | B10: Payable immediately Due net | C10: =VLOOKUP(A10,'KNVV--BSEG'!D:D,1,0) -> #N/A
B11: Baseline date on 10 of next month | C11: =VLOOKUP(A11,'KNVV--BSEG'!D:D,1,0) -> #N/A
A12: 0006 | B12: Before End of the month 4 % cash discount | C12: =VLOOKUP(A12,'KNVV--BSEG'!D:D,1,0) -> #N/A
B13: Before 15 of the next month ;; 2 % cash discount | C13: =VLOOKUP(A13,'KNVV--BSEG'!D:D,1,0) -> #N/A
B14: Before 15 in 2 months Due net | C14: =VLOOKUP(A14,'KNVV--BSEG'!D:D,1,0) -> #N/A
A15: 0007 | B15: For Invoicing up to 15 of Month | C15: =VLOOKUP(A15,'KNVV--BSEG'!D:D,1,0) -> #N/A
B16: Before 15 of the next month ;; 2 % cash discount | C16: =VLOOKUP(A16,'KNVV--BSEG'!D:D,1,0) -> #N/A
B17: Before End of the next month ;; Due net | C17: =VLOOKUP(A17,'KNVV--BSEG'!D:D,1,0) -> #N/A
B18: For Invoicing up to End of Month | C18: =VLOOKUP(A18,'KNVV--BSEG'!D:D,1,0) -> #N/A
B19: Before End of the next month ;; 2 % cash discoun | C19: =VLOOKUP(A19,'KNVV--BSEG'!D:D,1,0) -> #N/A
B20: Before 15 in 2 months Due net | C20: =VLOOKUP(A20,'KNVV--BSEG'!D:D,1,0) -> #N/A
A21: 0008 | B21: For Invoicing up to 15 of Month | C21: =VLOOKUP(A21,'KNVV--BSEG'!D:D,1,0) -> 0008 | D21: =B21&", "&B22&", "&B23&", "&B24&", "&B25&", "&B26&", "&B27&", "&B28&", "&B29&", "&B30 -> For Invoicing up to 15 of Month, within 14 days 2 % cash discount, within 30 days 1.5 % cash discount, within 45 days Due net, Baseline date on 30 of the month, For Invoicing up to End of Month, within 14 days 2 % cash discount, within 30 days 1.5 % cash discount, within 45 days Due net, Baseline date on 15 of next month
B22: within 14 days 2 % cash discount | C22: =VLOOKUP(A22,'KNVV--BSEG'!D:D,1,0) -> #N/A
B23: within 30 days 1.5 % cash discount | C23: =VLOOKUP(A23,'KNVV--BSEG'!D:D,1,0) -> #N/A
B24: within 45 days Due net | C24: =VLOOKUP(A24,'KNVV--BSEG'!D:D,1,0) -> #N/A
B25: Baseline date on 30 of the month | C25: =VLOOKUP(A25,'KNVV--BSEG'!D:D,1,0) -> #N/A
B26: For Invoicing up to End of Month | C26: =VLOOKUP(A26,'KNVV--BSEG'!D:D,1,0) -> #N/A
B27: within 14 days 2 % cash discount | C27: =VLOOKUP(A27,'KNVV--BSEG'!D:D,1,0) -> #N/A
B28: within 30 days 1.5 % cash discount | C28: =VLOOKUP(A28,'KNVV--BSEG'!D:D,1,0) -> #N/A
B29: within 45 days Due net | C29: =VLOOKUP(A29,'KNVV--BSEG'!D:D,1,0) -> #N/A
B30: Baseline date on 15 of next month | C30: =VLOOKUP(A30,'KNVV--BSEG'!D:D,1,0) -> #N/A
A31: 0009 | B31: Payable in 3 partial amounts | C31: =VLOOKUP(A31,'KNVV--BSEG'!D:D,1,0) -> #N/A
B32: 1 installment: 30.000 % with payment term 0001 | C32: =VLOOKUP(A32,'KNVV--BSEG'!D:D,1,0) -> #N/A
B33: 2 installment: 40.000 % with payment term 0001 | C33: =VLOOKUP(A33,'KNVV--BSEG'!D:D,1,0) -> #N/A
B34: 3 installment: 30.000 % with payment term 0001 | C34: =VLOOKUP(A34,'KNVV--BSEG'!D:D,1,0) -> #N/A
A35: 0200 | B35: Payable immediately Due net | C35: =VLOOKUP(A35,'KNVV--BSEG'!D:D,1,0) -> #N/A | D35: =B35 -> Payable immediately Due net
A36: 0201 | B36: Payable immediately Due net | C36: =VLOOKUP(A36,'KNVV--BSEG'!D:D,1,0) -> 0201 | D36: =B36 -> Payable immediately Due net
A37: 0430 | B37: within 14 days Due net | C37: =VLOOKUP(A37,'KNVV--BSEG'!D:D,1,0) -> #N/A
A38: 0450 | B38: within 20 days Due net | C38: =VLOOKUP(A38,'KNVV--BSEG'!D:D,1,0) -> #N/A
A39: 0455 | B39: within 25 days Due net | C39: =VLOOKUP(A39,'KNVV--BSEG'!D:D,1,0) -> #N/A
A40: 0460 | B40: within 30 days Due net | C40: =VLOOKUP(A40,'KNVV--BSEG'!D:D,1,0) -> 0460 | D40: =B40 -> within 30 days Due net
A41: 0475 | B41: within 31 days Due net | C41: =VLOOKUP(A41,'KNVV--BSEG'!D:D,1,0) -> #N/A
A42: 0480 | B42: within 35 days Due net | C42: =VLOOKUP(A42,'KNVV--BSEG'!D:D,1,0) -> #N/A | D42: =B42 -> within 35 days Due net
A43: 0500 | B43: within 40 days Due net | C43: =VLOOKUP(A43,'KNVV--BSEG'!D:D,1,0) -> #N/A
A44: 0520 | B44: within 45 days Due net | C44: =VLOOKUP(A44,'KNVV--BSEG'!D:D,1,0) -> 0520 | D44: =B44 -> within 45 days Due net
A45: 0525 | B45: within 55 days Due net | C45: =VLOOKUP(A45,'KNVV--BSEG'!D:D,1,0) -> #N/A
A46: 0526 | B46: within 33 days Due net | C46: =VLOOKUP(A46,'KNVV--BSEG'!D:D,1,0) -> #N/A
A47: 0527 | B47: within 110 days Due net | C47: =VLOOKUP(A47,'KNVV--BSEG'!D:D,1,0) -> #N/A | D47: =B47 -> within 110 days Due net
A48: 0528 | B48: within 80 days Due net | C48: =VLOOKUP(A48,'KNVV--BSEG'!D:D,1,0) -> #N/A | D48: =B48 -> within 80 days Due net
A49: 0529 | B49: within 90 days Due net | C49: =VLOOKUP(A49,'KNVV--BSEG'!D:D,1,0) -> #N/A | D49: =B49 -> within 90 days Due net
A50: 0530 | B50: within 50 days Due net | C50: =VLOOKUP(A50,'KNVV--BSEG'!D:D,1,0) -> #N/A
A51: 0531 | B51: within 90 days Due net | C51: =VLOOKUP(A51,'KNVV--BSEG'!D:D,1,0) -> #N/A
A52: 0532 | B52: within 65 days Due net | C52: =VLOOKUP(A52,'KNVV--BSEG'!D:D,1,0) -> #N/A
A53: 0533 | B53: within 47 days Due net | C53: =VLOOKUP(A53,'KNVV--BSEG'!D:D,1,0) -> #N/A
A54: 0534 | B54: within 60 days Due net | C54: =VLOOKUP(A54,'KNVV--BSEG'!D:D,1,0) -> #N/A
A55: 0535 | B55: within 55 days Due net | C55: =VLOOKUP(A55,'KNVV--BSEG'!D:D,1,0) -> 0535 | D55: =B55 -> within 55 days Due net
A56: 0540 | B56: within 60 days Due net | C56: =VLOOKUP(A56,'KNVV--BSEG'!D:D,1,0) -> 0540 | D56: =B56 -> within 60 days Due net
A57: 0545 | B57: within 70 days Due net | C57: =VLOOKUP(A57,'KNVV--BSEG'!D:D,1,0) -> #N/A
A58: 0546 | B58: within 55 days Due net | C58: =VLOOKUP(A58,'KNVV--BSEG'!D:D,1,0) -> #N/A
A59: 0550 | B59: within 105 days Due net | C59: =VLOOKUP(A59,'KNVV--BSEG'!D:D,1,0) -> #N/A
A60: 0560 | B60: within 75 days Due net | C60: =VLOOKUP(A60,'KNVV--BSEG'!D:D,1,0) -> #N/A | D60: =B60 -> within 75 days Due net
A61: 0561 | B61: within 44 days Due net | C61: =VLOOKUP(A61,'KNVV--BSEG'!D:D,1,0) -> #N/A
A62: 0570 | B62: within 85 days Due net | C62: =VLOOKUP(A62,'KNVV--BSEG'!D:D,1,0) -> #N/A
A63: 0580 | B63: within 90 days Due net | C63: =VLOOKUP(A63,'KNVV--BSEG'!D:D,1,0) -> #N/A | D63: =B63 -> within 90 days Due net
A64: 0600 | B64: within 120 days Due net | C64: =VLOOKUP(A64,'KNVV--BSEG'!D:D,1,0) -> #N/A | D64: =B64 -> within 120 days Due net
A65: 0640 | B65: within 180 days Due net | C65: =VLOOKUP(A65,'KNVV--BSEG'!D:D,1,0) -> #N/A | D65: =B65 -> within 180 days Due net
A66: 1011 | B66: Before End of the month Aft. 45 Days Due net | C66: =VLOOKUP(A66,'KNVV--BSEG'!D:D,1,0) -> #N/A
A67: 1284 | B67: within 22 days Due net | C67: =VLOOKUP(A67,'KNVV--BSEG'!D:D,1,0) -> #N/A
A68: 1310 | B68: within 10 days 4 % cash discount | C68: =VLOOKUP(A68,'KNVV--BSEG'!D:D,1,0) -> #N/A
B69: within 30 days Due net | C69: =VLOOKUP(A69,'KNVV--BSEG'!D:D,1,0) -> #N/A
A70: 1311 | B70: within 7 days 4 % cash discount | C70: =VLOOKUP(A70,'KNVV--BSEG'!D:D,1,0) -> #N/A
B71: within 30 days Due net | C71: =VLOOKUP(A71,'KNVV--BSEG'!D:D,1,0) -> #N/A
A72: 1385 | B72: within 14 days 2 % cash discount | C72: =VLOOKUP(A72,'KNVV--BSEG'!D:D,1,0) -> #N/A
B73: within 30 days Due net | C73: =VLOOKUP(A73,'KNVV--BSEG'!D:D,1,0) -> #N/A
A74: 1606 | B74: within 15 days 2 % cash discount | C74: =VLOOKUP(A74,'KNVV--BSEG'!D:D,1,0) -> #N/A
B75: within 30 days Due net | C75: =VLOOKUP(A75,'KNVV--BSEG'!D:D,1,0) -> #N/A
A76: 1940 | B76: within 60 days 3 % cash discount | C76: =VLOOKUP(A76,'KNVV--BSEG'!D:D,1,0) -> #N/A
B77: within 90 days Due net | C77: =VLOOKUP(A77,'KNVV--BSEG'!D:D,1,0) -> #N/A
A78: 2024 | B78: within 53 days Due net | C78: =VLOOKUP(A78,'KNVV--BSEG'!D:D,1,0) -> #N/A
A79: 3330 | B79: Before 15 of the next month ;; Due net | C79: =VLOOKUP(A79,'KNVV--BSEG'!D:D,1,0) -> #N/A
A80: 3350 | B80: Before 15 of the next month ;; Due net | C80: =VLOOKUP(A80,'KNVV--BSEG'!D:D,1,0) -> #N/A | D80: =B80 -> Before 15 of the next month ;; Due net
A81: 3360 | B81: Before 15 of the next month ;; 2 % cash discount | C81: =VLOOKUP(A81,'KNVV--BSEG'!D:D,1,0) -> #N/A
B82: within 90 days Due net | C82: =VLOOKUP(A82,'KNVV--BSEG'!D:D,1,0) -> #N/A
A83: 3440 | B83: Before 20 of the next month ;; Due net | C83: =VLOOKUP(A83,'KNVV--BSEG'!D:D,1,0) -> #N/A
A84: 3480 | B84: Before 25 of the next month ;; Due net | C84: =VLOOKUP(A84,'KNVV--BSEG'!D:D,1,0) -> #N/A | D84: =B84 -> Before 25 of the next month ;; Due net
A85: 3481 | B85: Before 25 of the next month ;; Due net | C85: =VLOOKUP(A85,'KNVV--BSEG'!D:D,1,0) -> #N/A
A86: 3500 | B86: Before 25 of the next month ;; 2 % cash discount | C86: =VLOOKUP(A86,'KNVV--BSEG'!D:D,1,0) -> #N/A
B87: within 60 days Due net | C87: =VLOOKUP(A87,'KNVV--BSEG'!D:D,1,0) -> #N/A
A88: 3600 | B88: Before End of the next month ;; Due net | C88: =VLOOKUP(A88,'KNVV--BSEG'!D:D,1,0) -> #N/A | D88: =B88 -> Before End of the next month ;; Due net
A89: 3640 | B89: Before End of the next month ;; 2 % cash discount | C89: =VLOOKUP(A89,'KNVV--BSEG'!D:D,1,0) -> #N/A
B90: within 63 days Due net | C90: =VLOOKUP(A90,'KNVV--BSEG'!D:D,1,0) -> #N/A
A91: 3663 | B91: For Invoicing up to End of Month | C91: =VLOOKUP(A91,'KNVV--BSEG'!D:D,1,0) -> #N/A
B92: Before 2 in 2 months Due net | C92: =VLOOKUP(A92,'KNVV--BSEG'!D:D,1,0) -> #N/A
A93: 3670 | B93: Before 15 in 2 months Due net | C93: =VLOOKUP(A93,'KNVV--BSEG'!D:D,1,0) -> #N/A
A94: 3690 | B94: For Invoicing up to End of Month | C94: =VLOOKUP(A94,'KNVV--BSEG'!D:D,1,0) -> #N/A | D94: =B94&", "&B95 -> For Invoicing up to End of Month, Before 20 in 2 months Due net
B95: Before 20 in 2 months Due net | C95: =VLOOKUP(A95,'KNVV--BSEG'!D:D,1,0) -> #N/A
A96: 3720 | B96: For Invoicing up to End of Month | C96: =VLOOKUP(A96,'KNVV--BSEG'!D:D,1,0) -> #N/A | D96: =B96&", "&B97 -> For Invoicing up to End of Month, Before 1 in 3 months Due net
B97: Before 1 in 3 months Due net | C97: =VLOOKUP(A97,'KNVV--BSEG'!D:D,1,0) -> #N/A
A98: 3760 | B98: For Invoicing up to End of Month | C98: =VLOOKUP(A98,'KNVV--BSEG'!D:D,1,0) -> #N/A | D98: =B98&", "&B99 -> For Invoicing up to End of Month, Before 15 in 3 months Due net
B99: Before 15 in 3 months Due net | C99: =VLOOKUP(A99,'KNVV--BSEG'!D:D,1,0) -> #N/A
A100: 3780 | B100: For Invoicing up to End of Month | C100: =VLOOKUP(A100,'KNVV--BSEG'!D:D,1,0) -> #N/A
...
